Sum_04767/__init__.py
Sum_04767-0.0.1.dist-info/Licence.txt
Sum_04767-0.0.1.dist-info/METADATA
Sum_04767-0.0.1.dist-info/WHEEL
Sum_04767-0.0.1.dist-info/top_level.txt
Sum_04767-0.0.1.dist-info/RECORD
