Metadata-Version: 2.1
Name: Sum-04767
Version: 0.0.1
Summary: adding number
Home-page: UNKNOWN
Author: Sami Ullah Baig
Author-email: samibaig72@gmail.com
License: UNKNOWN
Platform: UNKNOWN
Classifier: Programming Language :: Python :: 3
Classifier: License :: OSI Approved :: MIT License
Classifier: Operating System :: OS Independent
